asgi_request_id/__init__.py
asgi_request_id/middleware.py
asgi_request_id-0.2.1.dist-info/LICENSE
asgi_request_id-0.2.1.dist-info/METADATA
asgi_request_id-0.2.1.dist-info/WHEEL
asgi_request_id-0.2.1.dist-info/RECORD
