Metadata-Version: 2.1
Name: asgi-request-id
Version: 0.2.1
Summary: ASGI request id middleware
Home-page: https://github.com/arni-inaba/asgi-request-id
License: MIT
Author: Arni Inaba Kjartansson
Author-email: arni@inaba.is
Maintainer: Fabio Greco
Maintainer-email: fabio.greco.github@gmail.com
Requires-Python: >=3.6,<4.0
Classifier: License :: OSI Approved :: MIT License
Classifier: Programming Language :: Python :: 3
Classifier: Programming Language :: Python :: 3.6
Classifier: Programming Language :: Python :: 3.7
Classifier: Programming Language :: Python :: 3.8
Classifier: Programming Language :: Python :: 3.9
Classifier: Programming Language :: Python :: 3.10
Classifier: Programming Language :: Python :: 3.11
Classifier: Programming Language :: Python :: 3.12
Project-URL: Repository, https://github.com/arni-inaba/asgi-request-id
